nefelibata/__init__.py
nefelibata/config.py
nefelibata/console.py
nefelibata/constants.py
nefelibata/enclosure.py
nefelibata/post.py
nefelibata/utils.py
nefelibata/announcers/__init__.py
nefelibata/announcers/antenna.py
nefelibata/announcers/archive_blog.py
nefelibata/announcers/base.py
nefelibata/announcers/capcom.py
nefelibata/announcers/geminispace.py
nefelibata/announcers/gemlog.py
nefelibata/announcers/mastodon.py
nefelibata/announcers/webmention.py
nefelibata/assistants/__init__.py
nefelibata/assistants/archive_links.py
nefelibata/assistants/base.py
nefelibata/assistants/current_weather.py
nefelibata/assistants/mirror_images.py
nefelibata/assistants/news.py
nefelibata/assistants/playlist.py
nefelibata/assistants/reading_time.py
nefelibata/assistants/rsvp_calendar.py
nefelibata/builders/__init__.py
nefelibata/builders/base.py
nefelibata/builders/gemini.py
nefelibata/builders/html.py
nefelibata/cli/__init__.py
nefelibata/cli/build.py
nefelibata/cli/init.py
nefelibata/cli/new.py
nefelibata/cli/publish.py
nefelibata/publishers/__init__.py
nefelibata/publishers/base.py
nefelibata/publishers/command.py
nefelibata/publishers/ftp.py
nefelibata/publishers/s3.py
nefelibata/templates/builders/gemini/feed.gmi
nefelibata/templates/builders/gemini/group.gmi
nefelibata/templates/builders/gemini/index.gmi
nefelibata/templates/builders/gemini/like.gmi
nefelibata/templates/builders/gemini/post.gmi
nefelibata/templates/builders/gemini/rsvp.gmi
nefelibata/templates/builders/gemini/short.gmi
nefelibata/templates/builders/gemini/song.gmi
nefelibata/templates/builders/html/minimal/src/atom.xml
nefelibata/templates/builders/html/minimal/src/base.html
nefelibata/templates/builders/html/minimal/src/group.html
nefelibata/templates/builders/html/minimal/src/index.html
nefelibata/templates/builders/html/minimal/src/like.html
nefelibata/templates/builders/html/minimal/src/post.html
nefelibata/templates/builders/html/minimal/src/rsvp.html
nefelibata-0.4.dist-info/AUTHORS.rst
nefelibata-0.4.dist-info/LICENSE.txt
nefelibata-0.4.dist-info/METADATA
nefelibata-0.4.dist-info/WHEEL
nefelibata-0.4.dist-info/entry_points.txt
nefelibata-0.4.dist-info/top_level.txt
nefelibata-0.4.dist-info/RECORD
