Metadata-Version: 2.1
Name: nefelibata
Version: 0.4
Summary: A blog engine focusing on data ownership and persistence.
Home-page: https://github.com/betodealmeida/nefelibata/
Author: Beto Dealmeida
Author-email: roberto@dealmeida.net
License: MIT
Project-URL: Documentation, https://nefelibata.readthedocs.io/
Project-URL: Source, https://github.com/betodealmeida/nefelibata/
Project-URL: Tracker, https://github.com/betodealmeida/nefelibata/issues
Platform: any
Classifier: Development Status :: 4 - Beta
Classifier: Environment :: Web Environment
Classifier: License :: OSI Approved :: MIT License
Classifier: Programming Language :: Python :: 3.7
Classifier: Programming Language :: Python :: 3.8
Classifier: Programming Language :: Python :: 3.9
Requires-Python: >=3.7
License-File: LICENSE.txt
License-File: AUTHORS.rst
Requires-Dist: docopt (==0.6.2)
Requires-Dist: rich (<11,>=10.9.0)
Requires-Dist: PyYAML (<6,>=5.4.1)
Requires-Dist: pydantic (<2,>=1.8.2)
Requires-Dist: werkzeug (<3,>=2.0.1)
Requires-Dist: mutagen (<2,>=1.45.1)
Requires-Dist: jinja2 (<3,>=2.0.1)
Requires-Dist: marko (<2,>=1.1.0)
Requires-Dist: mastodon.py (<2,>=1.5.1)
Requires-Dist: aiohttp (<4,>=3.7.4.post0)
Requires-Dist: aiogemini (==0.2.0)
Requires-Dist: yarl (<2,>=1.6.3)
Requires-Dist: piexif (<2,>=1.1.3)
Requires-Dist: Pillow (<9,>=8.3.2)
Requires-Dist: boto3 (<2,>=1.18.53)
Requires-Dist: beautifulsoup4 (<5,>=4.10.0)
Requires-Dist: icalendar (<5,>=4.0.8)
Requires-Dist: mf2py (<2,>=1.1.2)
Requires-Dist: caldav (==0.8.0)
Requires-Dist: importlib-metadata ; python_version < "3.8"
Provides-Extra: docs
Requires-Dist: sphinx (<5,>=4.1.2) ; extra == 'docs'
Provides-Extra: testing
Requires-Dist: pytest (<7,>=6.2.5) ; extra == 'testing'
Requires-Dist: pytest-cov (<3,>=2.12.1) ; extra == 'testing'
Requires-Dist: pytest-mock (<4,>=3.6.1) ; extra == 'testing'
Requires-Dist: pyfakefs (<5,>=4.5.1) ; extra == 'testing'
Requires-Dist: pre-commit (<3,>=2.15.0) ; extra == 'testing'
Requires-Dist: freezegun (<2,>=1.1.0) ; extra == 'testing'
Requires-Dist: pytest-asyncio (==0.15.1) ; extra == 'testing'
Requires-Dist: codespell (<3,>=2.1.0) ; extra == 'testing'
Requires-Dist: pip-tools (<7,>=6.4.0) ; extra == 'testing'
